{
  "project_info": {
    "project_number": "728205946627",
    "project_id": "chatgva",
    "storage_bucket": "chatgva.firebasestorage.app"
  },
  "client": [
    {
      "client_info": {
        "mobilesdk_app_id": "1:728205946627:android:ee78624bdb6d72e4f78336",
        "android_client_info": {
          "package_name": "com.iabd"
        }
      },
      "oauth_client": [],
      "api_key": [
        {
          "current_key": "AIzaSyDF43dXUSNNyQooUHiGd9nWni5NBmUfHKc"
        }
      ],
      "services": {
        "appinvite_service": {
          "other_platform_oauth_client": []
        }
      }
    },
    {
      "client_info": {
        "mobilesdk_app_id": "1:728205946627:android:a6350a54d0faa704f78336",
        "android_client_info": {
          "package_name": "com.iabd.chatgva"
        }
      },
      "oauth_client": [],
      "api_key": [
        {
          "current_key": "AIzaSyDF43dXUSNNyQooUHiGd9nWni5NBmUfHKc"
        }
      ],
      "services": {
        "appinvite_service": {
          "other_platform_oauth_client": []
        }
      }
    }
  ],
  "configuration_version": "1"
}